testuthird/__init__.py
testuthird/main.py
testuthird/__system__/imports.py
testuthird/__system__/index.py
testuthird/__system__/modules/jobs.py
testuthird/__system__/sources/clight.json
testuthird/__system__/sources/logo.ico
testuthird-1.0.2.dist-info/METADATA
testuthird-1.0.2.dist-info/WHEEL
testuthird-1.0.2.dist-info/entry_points.txt
testuthird-1.0.2.dist-info/top_level.txt
testuthird-1.0.2.dist-info/RECORD
